clouduct/__init__.py
clouduct/clouduct.py
clouduct/console/__init__.py
clouduct/console/clouductbootstrap.py
clouduct/cookicutter/__init__.py
clouduct/cookicutter/project-to-cookiecutter.py
clouduct/reseed/__init__.py
clouduct/reseed/reseed.py
clouduct/reseed/reseed2.py
clouduct/simplecache.py
clouduct/tui.py
clouduct-bin/clouduct-tf
clouduct-0.0.2.dist-info/entry_points.txt
clouduct-0.0.2.dist-info/LICENSE
clouduct-0.0.2.dist-info/WHEEL
clouduct-0.0.2.dist-info/METADATA
clouduct-0.0.2.dist-info/RECORD
