Metadata-Version: 2.1
Name: clouduct
Version: 0.0.2
Summary: Bootstrap for Clouduct projects
Home-page: UNKNOWN
License: MPL-2.0
Author: Victor Volle
Author-email: victor.volle@beta-thoughts.org
Requires-Python: >=3.6,<4.0
Classifier: License :: OSI Approved
Classifier: Programming Language :: Python :: 3
Classifier: Programming Language :: Python :: 3.6
Classifier: Programming Language :: Python :: 3.7
Requires-Dist: GitPython (>=2.1,<3.0)
Requires-Dist: boto3 (>=1.7,<2.0)
Requires-Dist: click (>=6.7,<7.0)
Requires-Dist: click-completion
Requires-Dist: cookiecutter (>=1.6,<2.0)
Requires-Dist: npyscreen (>=4.10,<5.0)
Requires-Dist: pathspec (>=0.5.6,<0.6.0)
Requires-Dist: pyyaml (>=3.13,<4.0)
